sparql/__init__.py
sparql/admin.py
sparql/apps.py
sparql/forms.py
sparql/models.py
sparql/tests.py
sparql/urls.py
sparql/views.py
sparql/migrations/0001_initial.py
sparql/migrations/__init__.py
sparql/templates/sparql/query_view.html
acdh_django_sparql-0.0.1.dist-info/LICENSE.txt
acdh_django_sparql-0.0.1.dist-info/METADATA
acdh_django_sparql-0.0.1.dist-info/WHEEL
acdh_django_sparql-0.0.1.dist-info/top_level.txt
acdh_django_sparql-0.0.1.dist-info/RECORD
