Metadata-Version: 2.1
Name: acdh-django-sparql
Version: 0.0.1
Summary: Basic query interface and proxy for any common triple store.
Home-page: https://github.com/acdh-oeaw/acdh-django-sparql
Author: Peter Andorfer
Author-email: peter.andorfer@oeaw.ac.at
License: MIT License
Platform: UNKNOWN
Classifier: Environment :: Web Environment
Classifier: Framework :: Django
Classifier: Framework :: Django :: 2.0
Classifier: Intended Audience :: Developers
Classifier: License :: OSI Approved :: MIT License
Classifier: Operating System :: OS Independent
Classifier: Programming Language :: Python
Classifier: Programming Language :: Python :: 3.4
Classifier: Programming Language :: Python :: 3.5
Classifier: Programming Language :: Python :: 3.6
Classifier: Topic :: Internet :: WWW/HTTP
Classifier: Topic :: Internet :: WWW/HTTP :: Dynamic Content
Requires-Dist: Django (>=2.0)
Requires-Dist: rdflib (>=4.0)
Requires-Dist: SPARQLWrapper (==1.8.2)
